{"_id":{"$oid":"581d50fa23cdd2c137a30526"},"{\"_id\":{\"$oid\":\"581d500123cdd2c137a3050c\"}":"{\"_id\":{\"$oid\":\"581d500123cdd2c137a30514\"}","status":"status","Folio #":"Folio #","address":"address","city":"city","Zip Code":"Zip Code","agent_name":"agent_name","dom":"dom","dates_email_were_sent_on":"dates_email_were_sent_on","listPrice":"listPrice","offerPrice":"offerPrice","Offer":"Offer","C. Offer":"C. Offer","LU":"LU","C":"C","P":"P","E":"E","A":"A","Agent Type":"Agent Type","phone_no":"phone_no","email_address":"email_address","cell_phone":"cell_phone","comments":"comments","county":"county","owner":"owner","last_date_email_sent_on":"last_date_email_sent_on","no_of_emails_sent":"no_of_emails_sent","last_date_email_open":"last_date_email_open","no_of_emails_open":"no_of_emails_open","last_date_call_was_made":"last_date_call_was_made","call_priority":"call_priority","user_logged_in":"user_logged_in"}
{"_id":{"$oid":"581d50fa23cdd2c137a30521"},"{\"_id\":{\"$oid\":\"581d500123cdd2c137a3050c\"}":"{\"_id\":{\"$oid\":\"581d500123cdd2c137a3050d\"}","status":"status","Folio #":"Folio #","address":"address","city":"city","Zip Code":"Zip Code","agent_name":"agent_name","dom":"dom","dates_email_were_sent_on":"dates_email_were_sent_on","listPrice":"listPrice","offerPrice":"offerPrice","Offer":"Offer","C. Offer":"C. Offer","LU":"LU","C":"C","P":"P","E":"E","A":"A","Agent Type":"Agent Type","phone_no":"phone_no","email_address":"email_address","cell_phone":"cell_phone","comments":"comments","county":"county","owner":"owner","last_date_email_sent_on":"last_date_email_sent_on","no_of_emails_sent":"no_of_emails_sent","last_date_email_open":"last_date_email_open","no_of_emails_open":"no_of_emails_open","last_date_call_was_made":"last_date_call_was_made","call_priority":"call_priority","user_logged_in":"user_logged_in"}
{"_id":{"$oid":"581d50fa23cdd2c137a30522"},"{\"_id\":{\"$oid\":\"581d500123cdd2c137a3050c\"}":"{\"_id\":{\"$oid\":\"581d500123cdd2c137a3050f\"}","status":"status","Folio #":"Folio #","address":"address","city":"city","Zip Code":"Zip Code","agent_name":"agent_name","dom":"dom","dates_email_were_sent_on":"dates_email_were_sent_on","listPrice":"listPrice","offerPrice":"offerPrice","Offer":"Offer","C. Offer":"C. Offer","LU":"LU","C":"C","P":"P","E":"E","A":"A","Agent Type":"Agent Type","phone_no":"phone_no","email_address":"email_address","cell_phone":"cell_phone","comments":"comments","county":"county","owner":"owner","last_date_email_sent_on":"last_date_email_sent_on","no_of_emails_sent":"no_of_emails_sent","last_date_email_open":"last_date_email_open","no_of_emails_open":"no_of_emails_open","last_date_call_was_made":"last_date_call_was_made","call_priority":"call_priority","user_logged_in":"user_logged_in"}
{"_id":{"$oid":"581d50fa23cdd2c137a30524"},"{\"_id\":{\"$oid\":\"581d500123cdd2c137a3050c\"}":"{\"_id\":{\"$oid\":\"581d500123cdd2c137a30510\"}","status":"status","Folio #":"Folio #","address":"address","city":"city","Zip Code":"Zip Code","agent_name":"agent_name","dom":"dom","dates_email_were_sent_on":"dates_email_were_sent_on","listPrice":"listPrice","offerPrice":"offerPrice","Offer":"Offer","C. Offer":"C. Offer","LU":"LU","C":"C","P":"P","E":"E","A":"A","Agent Type":"Agent Type","phone_no":"phone_no","email_address":"email_address","cell_phone":"cell_phone","comments":"comments","county":"county","owner":"owner","last_date_email_sent_on":"last_date_email_sent_on","no_of_emails_sent":"no_of_emails_sent","last_date_email_open":"last_date_email_open","no_of_emails_open":"no_of_emails_open","last_date_call_was_made":"last_date_call_was_made","call_priority":"call_priority","user_logged_in":"user_logged_in"}
{"_id":{"$oid":"581d50fa23cdd2c137a30525"},"{\"_id\":{\"$oid\":\"581d500123cdd2c137a3050c\"}":"{\"_id\":{\"$oid\":\"581d500123cdd2c137a30512\"}","status":"status","Folio #":"Folio #","address":"address","city":"city","Zip Code":"Zip Code","agent_name":"agent_name","dom":"dom","dates_email_were_sent_on":"dates_email_were_sent_on","listPrice":"listPrice","offerPrice":"offerPrice","Offer":"Offer","C. Offer":"C. Offer","LU":"LU","C":"C","P":"P","E":"E","A":"A","Agent Type":"Agent Type","phone_no":"phone_no","email_address":"email_address","cell_phone":"cell_phone","comments":"comments","county":"county","owner":"owner","last_date_email_sent_on":"last_date_email_sent_on","no_of_emails_sent":"no_of_emails_sent","last_date_email_open":"last_date_email_open","no_of_emails_open":"no_of_emails_open","last_date_call_was_made":"last_date_call_was_made","call_priority":"call_priority","user_logged_in":"user_logged_in"}
{"_id":{"$oid":"581d50fa23cdd2c137a30520"},"{\"_id\":{\"$oid\":\"581d500123cdd2c137a3050c\"}":"{\"_id\":{\"$oid\":\"581d500123cdd2c137a3050e\"}","status":"status","Folio #":"Folio #","address":"address","city":"city","Zip Code":"Zip Code","agent_name":"agent_name","dom":"dom","dates_email_were_sent_on":"dates_email_were_sent_on","listPrice":"listPrice","offerPrice":"offerPrice","Offer":"Offer","C. Offer":"C. Offer","LU":"LU","C":"C","P":"P","E":"E","A":"A","Agent Type":"Agent Type","phone_no":"phone_no","email_address":"email_address","cell_phone":"cell_phone","comments":"comments","county":"county","owner":"owner","last_date_email_sent_on":"last_date_email_sent_on","no_of_emails_sent":"no_of_emails_sent","last_date_email_open":"last_date_email_open","no_of_emails_open":"no_of_emails_open","last_date_call_was_made":"last_date_call_was_made","call_priority":"call_priority","user_logged_in":"user_logged_in"}
{"_id":{"$oid":"581d50fa23cdd2c137a30528"},"{\"_id\":{\"$oid\":\"581d500123cdd2c137a3050c\"}":"{\"_id\":{\"$oid\":\"581d500123cdd2c137a30516\"}","status":"status","Folio #":"Folio #","address":"address","city":"city","Zip Code":"Zip Code","agent_name":"agent_name","dom":"dom","dates_email_were_sent_on":"dates_email_were_sent_on","listPrice":"listPrice","offerPrice":"offerPrice","Offer":"Offer","C. Offer":"C. Offer","LU":"LU","C":"C","P":"P","E":"E","A":"A","Agent Type":"Agent Type","phone_no":"phone_no","email_address":"email_address","cell_phone":"cell_phone","comments":"comments","county":"county","owner":"owner","last_date_email_sent_on":"last_date_email_sent_on","no_of_emails_sent":"no_of_emails_sent","last_date_email_open":"last_date_email_open","no_of_emails_open":"no_of_emails_open","last_date_call_was_made":"last_date_call_was_made","call_priority":"call_priority","user_logged_in":"user_logged_in"}
{"_id":{"$oid":"581d50fa23cdd2c137a3052a"},"{\"_id\":{\"$oid\":\"581d500123cdd2c137a3050c\"}":"{\"_id\":{\"$oid\":\"581d500123cdd2c137a30518\"}","status":"status","Folio #":"Folio #","address":"address","city":"city","Zip Code":"Zip Code","agent_name":"agent_name","dom":"dom","dates_email_were_sent_on":"dates_email_were_sent_on","listPrice":"listPrice","offerPrice":"offerPrice","Offer":"Offer","C. Offer":"C. Offer","LU":"LU","C":"C","P":"P","E":"E","A":"A","Agent Type":"Agent Type","phone_no":"phone_no","email_address":"email_address","cell_phone":"cell_phone","comments":"comments","county":"county","owner":"owner","last_date_email_sent_on":"last_date_email_sent_on","no_of_emails_sent":"no_of_emails_sent","last_date_email_open":"last_date_email_open","no_of_emails_open":"no_of_emails_open","last_date_call_was_made":"last_date_call_was_made","call_priority":"call_priority","user_logged_in":"user_logged_in"}
{"_id":{"$oid":"581d50fa23cdd2c137a3052b"},"{\"_id\":{\"$oid\":\"581d500123cdd2c137a3050c\"}":"{\"_id\":{\"$oid\":\"581d500123cdd2c137a3051a\"}","status":"status","Folio #":"Folio #","address":"address","city":"city","Zip Code":"Zip Code","agent_name":"agent_name","dom":"dom","dates_email_were_sent_on":"dates_email_were_sent_on","listPrice":"listPrice","offerPrice":"offerPrice","Offer":"Offer","C. Offer":"C. Offer","LU":"LU","C":"C","P":"P","E":"E","A":"A","Agent Type":"Agent Type","phone_no":"phone_no","email_address":"email_address","cell_phone":"cell_phone","comments":"comments","county":"county","owner":"owner","last_date_email_sent_on":"last_date_email_sent_on","no_of_emails_sent":"no_of_emails_sent","last_date_email_open":"last_date_email_open","no_of_emails_open":"no_of_emails_open","last_date_call_was_made":"last_date_call_was_made","call_priority":"call_priority","user_logged_in":"user_logged_in"}
{"_id":{"$oid":"581d50fa23cdd2c137a30529"},"{\"_id\":{\"$oid\":\"581d500123cdd2c137a3050c\"}":"{\"_id\":{\"$oid\":\"581d500123cdd2c137a30517\"}","status":"status","Folio #":"Folio #","address":"address","city":"city","Zip Code":"Zip Code","agent_name":"agent_name","dom":"dom","dates_email_were_sent_on":"dates_email_were_sent_on","listPrice":"listPrice","offerPrice":"offerPrice","Offer":"Offer","C. Offer":"C. Offer","LU":"LU","C":"C","P":"P","E":"E","A":"A","Agent Type":"Agent Type","phone_no":"email_address","email_address":"cell_phone","cell_phone":"comments","comments":"county","county":"owner","owner":"last_date_email_sent_on","last_date_email_sent_on":"no_of_emails_sent","no_of_emails_sent":"last_date_email_open","last_date_email_open":"no_of_emails_open","no_of_emails_open":"last_date_call_was_made","last_date_call_was_made":"call_priority","call_priority":"user_logged_in","user_logged_in":""}
{"_id":{"$oid":"581d50fa23cdd2c137a3052d"},"{\"_id\":{\"$oid\":\"581d500123cdd2c137a3050c\"}":"{\"_id\":{\"$oid\":\"581d500123cdd2c137a3051c\"}","status":"status","Folio #":"Folio #","address":"address","city":"city","Zip Code":"Zip Code","agent_name":"agent_name","dom":"dom","dates_email_were_sent_on":"dates_email_were_sent_on","listPrice":"listPrice","offerPrice":"offerPrice","Offer":"Offer","C. Offer":"C. Offer","LU":"LU","C":"C","P":"P","E":"E","A":"A","Agent Type":"Agent Type","phone_no":"phone_no","email_address":"email_address","cell_phone":"cell_phone","comments":"comments","county":"county","owner":"owner","last_date_email_sent_on":"last_date_email_sent_on","no_of_emails_sent":"no_of_emails_sent","last_date_email_open":"last_date_email_open","no_of_emails_open":"no_of_emails_open","last_date_call_was_made":"last_date_call_was_made","call_priority":"call_priority","user_logged_in":"user_logged_in"}
{"_id":{"$oid":"581d50fa23cdd2c137a3052e"},"{\"_id\":{\"$oid\":\"581d500123cdd2c137a3050c\"}":"{\"_id\":{\"$oid\":\"581d500123cdd2c137a30519\"}","status":"status","Folio #":"Folio #","address":"address","city":"city","Zip Code":"Zip Code","agent_name":"agent_name","dom":"dom","dates_email_were_sent_on":"dates_email_were_sent_on","listPrice":"listPrice","offerPrice":"offerPrice","Offer":"Offer","C. Offer":"C. Offer","LU":"LU","C":"C","P":"P","E":"E","A":"A","Agent Type":"Agent Type","phone_no":"phone_no","email_address":"email_address","cell_phone":"cell_phone","comments":"comments","county":"county","owner":"owner","last_date_email_sent_on":"last_date_email_sent_on","no_of_emails_sent":"no_of_emails_sent","last_date_email_open":"last_date_email_open","no_of_emails_open":"no_of_emails_open","last_date_call_was_made":"last_date_call_was_made","call_priority":"call_priority","user_logged_in":"user_logged_in"}
{"_id":{"$oid":"581d50fa23cdd2c137a3052f"},"{\"_id\":{\"$oid\":\"581d500123cdd2c137a3050c\"}":"{\"_id\":{\"$oid\":\"581d500123cdd2c137a3051e\"}","status":"status","Folio #":"Folio #","address":"address","city":"city","Zip Code":"Zip Code","agent_name":"agent_name","dom":"dom","dates_email_were_sent_on":"dates_email_were_sent_on","listPrice":"listPrice","offerPrice":"offerPrice","Offer":"Offer","C. Offer":"C. Offer","LU":"LU","C":"C","P":"P","E":"E","A":"A","Agent Type":"Agent Type","phone_no":"phone_no","email_address":"email_address","cell_phone":"cell_phone","comments":"comments","county":"county","owner":"owner","last_date_email_sent_on":"last_date_email_sent_on","no_of_emails_sent":"no_of_emails_sent","last_date_email_open":"last_date_email_open","no_of_emails_open":"no_of_emails_open","last_date_call_was_made":"last_date_call_was_made","call_priority":"call_priority","user_logged_in":"user_logged_in"}
{"_id":{"$oid":"581d50fa23cdd2c137a30530"},"{\"_id\":{\"$oid\":\"581d500123cdd2c137a3050c\"}":"{\"_id\":{\"$oid\":\"581d500123cdd2c137a3051d\"}","status":"status","Folio #":"Folio #","address":"address","city":"city","Zip Code":"Zip Code","agent_name":"agent_name","dom":"dom","dates_email_were_sent_on":"dates_email_were_sent_on","listPrice":"listPrice","offerPrice":"offerPrice","Offer":"Offer","C. Offer":"C. Offer","LU":"LU","C":"C","P":"P","E":"E","A":"A","Agent Type":"Agent Type","phone_no":"phone_no","email_address":"email_address","cell_phone":"cell_phone","comments":"comments","county":"county","owner":"owner","last_date_email_sent_on":"last_date_email_sent_on","no_of_emails_sent":"no_of_emails_sent","last_date_email_open":"last_date_email_open","no_of_emails_open":"no_of_emails_open","last_date_call_was_made":"last_date_call_was_made","call_priority":"call_priority","user_logged_in":"user_logged_in"}
{"_id":{"$oid":"581d50fa23cdd2c137a30531"},"{\"_id\":{\"$oid\":\"581d500123cdd2c137a3050c\"}":"{\"_id\":{\"$oid\":\"581d500123cdd2c137a3051f\"}","status":"status","Folio #":"Folio #","address":"address","city":"city","Zip Code":"Zip Code","agent_name":"agent_name","dom":"dom","dates_email_were_sent_on":"dates_email_were_sent_on","listPrice":"listPrice","offerPrice":"offerPrice","Offer":"Offer","C. Offer":"C. Offer","LU":"LU","C":"C","P":"P","E":"E","A":"A","Agent Type":"Agent Type","phone_no":"phone_no","email_address":"email_address","cell_phone":"cell_phone","comments":"comments","county":"county","owner":"owner","last_date_email_sent_on":"last_date_email_sent_on","no_of_emails_sent":"no_of_emails_sent","last_date_email_open":"last_date_email_open","no_of_emails_open":"no_of_emails_open","last_date_call_was_made":"last_date_call_was_made","call_priority":"call_priority","user_logged_in":"user_logged_in"}
{"_id":{"$oid":"581d50fa23cdd2c137a30532"},"{\"_id\":{\"$oid\":\"581d500123cdd2c137a3050c\"}":"{\"_id\":{\"$oid\":\"581d500123cdd2c137a30515\"}","status":"status","Folio #":"Folio #","address":"address","city":"city","Zip Code":"Zip Code","agent_name":"agent_name","dom":"dom","dates_email_were_sent_on":"dates_email_were_sent_on","listPrice":"listPrice","offerPrice":"offerPrice","Offer":"Offer","C. Offer":"C. Offer","LU":"LU","C":"C","P":"P","E":"E","A":"A","Agent Type":"Agent Type","phone_no":"phone_no","email_address":"email_address","cell_phone":"cell_phone","comments":"comments","county":"county","owner":"owner","last_date_email_sent_on":"last_date_email_sent_on","no_of_emails_sent":"no_of_emails_sent","last_date_email_open":"last_date_email_open","no_of_emails_open":"no_of_emails_open","last_date_call_was_made":"last_date_call_was_made","call_priority":"call_priority","user_logged_in":"user_logged_in"}
{"_id":{"$oid":"581d50fa23cdd2c137a3052c"},"{\"_id\":{\"$oid\":\"581d500123cdd2c137a3050c\"}":"{\"_id\":{\"$oid\":\"581d500123cdd2c137a3051b\"}","status":"status","Folio #":"Folio #","address":"address","city":"city","Zip Code":"Zip Code","agent_name":"agent_name","dom":"dom","dates_email_were_sent_on":"dates_email_were_sent_on","listPrice":"listPrice","offerPrice":"offerPrice","Offer":"Offer","C. Offer":"C. Offer","LU":"LU","C":"C","P":"P","E":"E","A":"A","Agent Type":"Agent Type","phone_no":"phone_no","email_address":"email_address","cell_phone":"cell_phone","comments":"comments","county":"county","owner":"owner","last_date_email_sent_on":"last_date_email_sent_on","no_of_emails_sent":"no_of_emails_sent","last_date_email_open":"last_date_email_open","no_of_emails_open":"no_of_emails_open","last_date_call_was_made":"last_date_call_was_made","call_priority":"call_priority","user_logged_in":"user_logged_in"}
{"_id":{"$oid":"581d50fa23cdd2c137a30527"},"{\"_id\":{\"$oid\":\"581d500123cdd2c137a3050c\"}":"{\"_id\":{\"$oid\":\"581d500123cdd2c137a30513\"}","status":"status","Folio #":"Folio #","address":"address","city":"city","Zip Code":"Zip Code","agent_name":"agent_name","dom":"dom","dates_email_were_sent_on":"dates_email_were_sent_on","listPrice":"listPrice","offerPrice":"offerPrice","Offer":"Offer","C. Offer":"C. Offer","LU":"LU","C":"C","P":"P","E":"E","A":"A","Agent Type":"Agent Type","phone_no":"phone_no","email_address":"email_address","cell_phone":"cell_phone","comments":"comments","county":"county","owner":"owner","last_date_email_sent_on":"last_date_email_sent_on","no_of_emails_sent":"no_of_emails_sent","last_date_email_open":"last_date_email_open","no_of_emails_open":"no_of_emails_open","last_date_call_was_made":"last_date_call_was_made","call_priority":"call_priority","user_logged_in":"user_logged_in"}
{"_id":{"$oid":"581d50fa23cdd2c137a30523"},"{\"_id\":{\"$oid\":\"581d500123cdd2c137a3050c\"}":"{\"_id\":{\"$oid\":\"581d500123cdd2c137a30511\"}","status":"status","Folio #":"Folio #","address":"address","city":"city","Zip Code":"Zip Code","agent_name":"agent_name","dom":"dom","dates_email_were_sent_on":"dates_email_were_sent_on","listPrice":"listPrice","offerPrice":"offerPrice","Offer":"Offer","C. Offer":"C. Offer","LU":"LU","C":"C","P":"P","E":"E","A":"A","Agent Type":"Agent Type","phone_no":"phone_no","email_address":"email_address","cell_phone":"cell_phone","comments":"comments","county":"county","owner":"owner","last_date_email_sent_on":"last_date_email_sent_on","no_of_emails_sent":"no_of_emails_sent","last_date_email_open":"last_date_email_open","no_of_emails_open":"no_of_emails_open","last_date_call_was_made":"last_date_call_was_made","call_priority":"call_priority","user_logged_in":"user_logged_in"}
